{
    "count": 2,
    "tasks": [
        {
            "id": 3,
            "name": "AutoRegTask - 080027670412",
            "checkInTime": "2025-03-05 09:31:52",
            "hostID": 3,
            "stateID": 3,
            "createdTime": "2025-03-05 09:31:31",
            "createdBy": "fog",
            "isForced": "0",
            "scheduledStartTime": "0000-00-00 00:00:00",
            "typeID": 1,
            "pct": "0000000100",
            "bpm": "11.28GB",
            "timeElapsed": "00:09:23",
            "timeRemaining": "00:00:00",
            "dataCopied": "98.601 GiB",
            "percent": "99.97",
            "dataTotal": "98.630 GiB",
            "storagegroupID": 1,
            "storagenodeID": 1,
            "NFSFailures": "",
            "NFSLastMemberID": 0,
            "shutdown": "",
            "passreset": "",
            "isDebug": 0,
            "imageID": 1,
            "wol": "0",
            "image": {
                "imageTypeID": 1,
                "imagePartitionTypeID": 1,
                "id": 1,
                "name": "Ubuntu testi",
                "description": "",
                "path": "Ubuntutesti",
                "createdTime": "2025-02-12 08:53:01",
                "createdBy": "fog",
                "building": 0,
                "size": "1048576.000000:51415.000000:210595840.000000:105903030272.000000:",
                "osID": 50,
                "deployed": "2025-02-12 11:27:37",
                "format": "5",
                "magnet": "",
                "protected": 0,
                "compress": 6,
                "isEnabled": "1",
                "toReplicate": "1",
                "srvsize": 1978310820,
                "os": {},
                "imagepartitiontype": {},
                "imagetype": {}
            },
            "host": {
                "id": 3,
                "name": "080027670412",
                "description": "Created by FOG Reg on March 3, 2025, 8:27 am",
                "ip": "",
                "imageID": 0,
                "building": 0,
                "createdTime": "2025-03-03 08:27:47",
                "deployed": "0000-00-00 00:00:00",
                "createdBy": "fog",
                "useAD": "",
                "ADDomain": "",
                "ADOU": "",
                "ADUser": "",
                "ADPass": "",
                "ADPassLegacy": "",
                "productKey": "",
                "printerLevel": "",
                "kernelArgs": "",
                "kernel": "",
                "kernelDevice": "",
                "init": "",
                "pending": "",
                "pub_key": "",
                "sec_tok": "",
                "sec_time": "0000-00-00 00:00:00",
                "pingstatus": "<i class=\"icon-ping-down fa fa-exclamation-circle red\" data-toggle=\"tooltip\" data-placement=\"right\" title=\"Unknown\"></i>",
                "biosexit": "",
                "efiexit": "",
                "enforce": "",
                "token": "",
                "tokenlock": 0,
                "primac": "08:00:27:67:04:12",
                "imagename": "Ubuntu testi",
                "hostscreen": {
                    "id": null,
                    "hostID": null,
                    "width": null,
                    "height": null,
                    "refresh": null,
                    "orientation": null,
                    "other1": null,
                    "other2": null
                },
                "hostalo": {
                    "id": null,
                    "hostID": null,
                    "time": null
                },
                "inventory": {
                    "id": 3,
                    "hostID": 3,
                    "primaryUser": "",
                    "other1": "",
                    "other2": "",
                    "createdTime": "2025-03-03 08:28:00",
                    "deleteDate": "0000-00-00 00:00:00",
                    "sysman": "innotek GmbH",
                    "sysproduct": "VirtualBox",
                    "sysversion": "1.2",
                    "sysserial": "VirtualBox-771e2002-910c-45c5-9e3b-105081bc7d3c",
                    "sysuuid": "02201e77-0c91-c545-9e3b-105081bc7d3c",
                    "systype": "Type: Other",
                    "biosversion": "VirtualBox",
                    "biosvendor": "innotek GmbH",
                    "biosdate": "12/01/2006",
                    "mbman": "Oracle Corporation",
                    "mbproductname": "VirtualBox",
                    "mbversion": "1.2",
                    "mbserial": "0",
                    "mbasset": "Not Specified",
                    "cpuman": "",
                    "cpuversion": "",
                    "cpucurrent": "",
                    "cpumax": "",
                    "mem": "MemTotal: 2023784 kB",
                    "hdmodel": "VBOX HARDDISK",
                    "hdserial": "VB3171f442-26a99fdd",
                    "hdfirmware": "1.0",
                    "caseman": "Oracle Corporation",
                    "casever": "Not Specified",
                    "caseserial": "Not Specified",
                    "caseasset": "Not Specified",
                    "gpuvendors": "VMware",
                    "gpuproducts": "SVGA II Adapter",
                    "memory": "1.93 GiB"
                },
                "image": {
                    "imageTypeID": 1,
                    "imagePartitionTypeID": 1,
                    "id": 1,
                    "name": "Ubuntu testi",
                    "description": "",
                    "path": "Ubuntutesti",
                    "createdTime": "2025-02-12 08:53:01",
                    "createdBy": "fog",
                    "building": 0,
                    "size": "1048576.000000:51415.000000:210595840.000000:105903030272.000000:",
                    "osID": 50,
                    "deployed": "2025-02-12 11:27:37",
                    "format": "5",
                    "magnet": "",
                    "protected": 0,
                    "compress": 6,
                    "isEnabled": "1",
                    "toReplicate": "1",
                    "srvsize": 1978310820,
                    "os": {},
                    "imagepartitiontype": {},
                    "imagetype": {}
                },
                "pingstatuscode": 6,
                "pingstatustext": "No such device or address",
                "macs": [
                    "08:00:27:67:04:12"
                ]
            },
            "type": {
                "id": 1,
                "name": "Deploy",
                "description": "Deploy action will send an image saved on the FOG server to the client computer with all included snapins.",
                "icon": "download",
                "kernel": "",
                "kernelArgs": "type=down",
                "type": "fog",
                "isAdvanced": "0",
                "access": "both",
                "initrd": ""
            },
            "state": {
                "id": 3,
                "name": "In-Progress",
                "description": "Host is currently Imaging.",
                "order": 3,
                "icon": "spinner fa-pulse fa-fw"
            },
            "storagenode": {
                "id": 1,
                "name": "DefaultMember",
                "description": "Auto generated fog nfs group member",
                "isMaster": "1",
                "storagegroupID": 1,
                "isEnabled": "1",
                "isGraphEnabled": "1",
                "path": "/images",
                "ftppath": "/images/",
                "bitrate": null,
                "helloInterval": null,
                "snapinpath": "/opt/fog/snapins",
                "sslpath": "/opt/fog/snapins/ssl",
                "ip": "192.168.100.10",
                "maxClients": 10,
                "user": "fogproject",
                "pass": "Kb1iMq5NaA*bnsPQynlN",
                "key": "",
                "interface": "enp0s3",
                "bandwidth": 0,
                "webroot": "/fog/",
                "storagegroup": {}
            },
            "storagegroup": {
                "id": 1,
                "name": "default",
                "description": "Auto generated fog nfs group"
            }
        },
        {
            "id": 1,
            "name": "Capture Task - 08002795bd8f",
            "checkInTime": "2025-02-12 09:22:10",
            "hostID": 1,
            "stateID": 4,
            "createdTime": "2025-02-12 09:20:57",
            "createdBy": "fog",
            "isForced": "0",
            "scheduledStartTime": "0000-00-00 00:00:00",
            "typeID": 2,
            "pct": "0000000100",
            "bpm": "6.24GB",
            "timeElapsed": "00:16:58",
            "timeRemaining": "00:00:00",
            "dataCopied": "98.557 GiB",
            "percent": "100",
            "dataTotal": "98.630 GiB",
            "storagegroupID": 1,
            "storagenodeID": 1,
            "NFSFailures": "",
            "NFSLastMemberID": 0,
            "shutdown": "",
            "passreset": "",
            "isDebug": 0,
            "imageID": 1,
            "wol": "1",
            "image": {
                "imageTypeID": 1,
                "imagePartitionTypeID": 1,
                "id": 1,
                "name": "Ubuntu testi",
                "description": "",
                "path": "Ubuntutesti",
                "createdTime": "2025-02-12 08:53:01",
                "createdBy": "fog",
                "building": 0,
                "size": "1048576.000000:51415.000000:210595840.000000:105903030272.000000:",
                "osID": 50,
                "deployed": "2025-02-12 11:27:37",
                "format": "5",
                "magnet": "",
                "protected": 0,
                "compress": 6,
                "isEnabled": "1",
                "toReplicate": "1",
                "srvsize": 1978310820,
                "os": {},
                "imagepartitiontype": {},
                "imagetype": {}
            },
            "host": {
                "id": 1,
                "name": "08002795bd8f",
                "description": "Created by FOG Reg on February 12, 2025, 8:43 am",
                "ip": "",
                "imageID": 1,
                "building": 0,
                "createdTime": "2025-02-12 08:43:13",
                "deployed": "0000-00-00 00:00:00",
                "createdBy": "fog",
                "useAD": "",
                "ADDomain": "",
                "ADOU": "",
                "ADUser": "",
                "ADPass": "",
                "ADPassLegacy": "",
                "productKey": "",
                "printerLevel": "",
                "kernelArgs": "",
                "kernel": "",
                "kernelDevice": "",
                "init": "",
                "pending": "",
                "pub_key": "",
                "sec_tok": "",
                "sec_time": "0000-00-00 00:00:00",
                "pingstatus": "<i class=\"icon-ping-down fa fa-exclamation-circle red\" data-toggle=\"tooltip\" data-placement=\"right\" title=\"Unknown\"></i>",
                "biosexit": "",
                "efiexit": "",
                "enforce": "",
                "token": "f31fa7885e4c9b5525103a802c4a9c198efeff4e4c6ec4c01ae96f6d84298c9ebd0cf3052239aa900bab54e249848b73eec4f33c8ee846cc545e8443c8e0fc19",
                "tokenlock": 0,
                "primac": "08:00:27:95:bd:8f",
                "imagename": "Ubuntu testi",
                "hostscreen": {
                    "id": null,
                    "hostID": null,
                    "width": null,
                    "height": null,
                    "refresh": null,
                    "orientation": null,
                    "other1": null,
                    "other2": null
                },
                "hostalo": {
                    "id": null,
                    "hostID": null,
                    "time": null
                },
                "inventory": {
                    "id": 1,
                    "hostID": 1,
                    "primaryUser": "",
                    "other1": "",
                    "other2": "",
                    "createdTime": "2025-02-12 08:43:25",
                    "deleteDate": "0000-00-00 00:00:00",
                    "sysman": "innotek GmbH",
                    "sysproduct": "VirtualBox",
                    "sysversion": "1.2",
                    "sysserial": "VirtualBox-2b24aad6-2ce9-4555-9701-7d93a480c50e",
                    "sysuuid": "d6aa242b-e92c-5545-9701-7d93a480c50e",
                    "systype": "Type: Other",
                    "biosversion": "VirtualBox",
                    "biosvendor": "innotek GmbH",
                    "biosdate": "12/01/2006",
                    "mbman": "Oracle Corporation",
                    "mbproductname": "VirtualBox",
                    "mbversion": "1.2",
                    "mbserial": "0",
                    "mbasset": "Not Specified",
                    "cpuman": "",
                    "cpuversion": "",
                    "cpucurrent": "",
                    "cpumax": "",
                    "mem": "MemTotal: 2023784 kB",
                    "hdmodel": "VBOX HARDDISK",
                    "hdserial": "VB8ab6c758-1eced72c",
                    "hdfirmware": "1.0",
                    "caseman": "Oracle Corporation",
                    "casever": "Not Specified",
                    "caseserial": "Not Specified",
                    "caseasset": "Not Specified",
                    "gpuvendors": "VMware",
                    "gpuproducts": "SVGA II Adapter",
                    "memory": "1.93 GiB"
                },
                "image": {
                    "imageTypeID": 1,
                    "imagePartitionTypeID": 1,
                    "id": 1,
                    "name": "Ubuntu testi",
                    "description": "",
                    "path": "Ubuntutesti",
                    "createdTime": "2025-02-12 08:53:01",
                    "createdBy": "fog",
                    "building": 0,
                    "size": "1048576.000000:51415.000000:210595840.000000:105903030272.000000:",
                    "osID": 50,
                    "deployed": "2025-02-12 11:27:37",
                    "format": "5",
                    "magnet": "",
                    "protected": 0,
                    "compress": 6,
                    "isEnabled": "1",
                    "toReplicate": "1",
                    "srvsize": 1978310820,
                    "os": {},
                    "imagepartitiontype": {},
                    "imagetype": {}
                },
                "pingstatuscode": 6,
                "pingstatustext": "No such device or address",
                "macs": [
                    "08:00:27:95:bd:8f"
                ]
            },
            "type": {
                "id": 2,
                "name": "Capture",
                "description": "Capture will pull an image from a client computer that will be saved on the server.",
                "icon": "upload",
                "kernel": "",
                "kernelArgs": "type=up",
                "type": "fog",
                "isAdvanced": "0",
                "access": "host",
                "initrd": ""
            },
            "state": {
                "id": 4,
                "name": "Complete",
                "description": "Imaging has been completed.",
                "order": 4,
                "icon": "check-circle"
            },
            "storagenode": {
                "id": 1,
                "name": "DefaultMember",
                "description": "Auto generated fog nfs group member",
                "isMaster": "1",
                "storagegroupID": 1,
                "isEnabled": "1",
                "isGraphEnabled": "1",
                "path": "/images",
                "ftppath": "/images/",
                "bitrate": null,
                "helloInterval": null,
                "snapinpath": "/opt/fog/snapins",
                "sslpath": "/opt/fog/snapins/ssl",
                "ip": "192.168.100.10",
                "maxClients": 10,
                "user": "fogproject",
                "pass": "Kb1iMq5NaA*bnsPQynlN",
                "key": "",
                "interface": "enp0s3",
                "bandwidth": 0,
                "webroot": "/fog/",
                "storagegroup": {}
            },
            "storagegroup": {
                "id": 1,
                "name": "default",
                "description": "Auto generated fog nfs group"
            }
        }
    ]
}